[
  {
    "paths": ["group1-shard1of1.bin"],
    "weights": [
      {
        "name": "model.pitch_emb.weight",
        "shape": [89, 32],
        "dtype": "float32"
      },
      {
        "name": "model.input_linear.weight",
        "shape": [128, 35],
        "dtype": "float32"
      },
      { "name": "model.input_linear.bias", "shape": [128], "dtype": "float32" },
      {
        "name": "model.cells.0.weight_ih",
        "shape": [512, 128],
        "dtype": "float32"
      },
      {
        "name": "model.cells.0.weight_hh",
        "shape": [512, 128],
        "dtype": "float32"
      },
      { "name": "model.cells.0.bias_ih", "shape": [512], "dtype": "float32" },
      { "name": "model.cells.0.bias_hh", "shape": [512], "dtype": "float32" },
      {
        "name": "model.cells.1.weight_ih",
        "shape": [512, 128],
        "dtype": "float32"
      },
      {
        "name": "model.cells.1.weight_hh",
        "shape": [512, 128],
        "dtype": "float32"
      },
      { "name": "model.cells.1.bias_ih", "shape": [512], "dtype": "float32" },
      { "name": "model.cells.1.bias_hh", "shape": [512], "dtype": "float32" },
      {
        "name": "model.beat_head.0.weight",
        "shape": [128, 128],
        "dtype": "float32"
      },
      { "name": "model.beat_head.0.bias", "shape": [128], "dtype": "float32" },
      {
        "name": "model.beat_head.3.weight",
        "shape": [1, 128],
        "dtype": "float32"
      },
      { "name": "model.beat_head.3.bias", "shape": [1], "dtype": "float32" },
      {
        "name": "model.downbeat_head.0.weight",
        "shape": [128, 128],
        "dtype": "float32"
      },
      {
        "name": "model.downbeat_head.0.bias",
        "shape": [128],
        "dtype": "float32"
      },
      {
        "name": "model.downbeat_head.3.weight",
        "shape": [1, 128],
        "dtype": "float32"
      },
      { "name": "model.downbeat_head.3.bias", "shape": [1], "dtype": "float32" }
    ]
  }
]
